calculator_775c57ddfd6f4cfb/__init__.py
calculator_775c57ddfd6f4cfb/calculator.py
calculator_775c57ddfd6f4cfb-0.0.2.dist-info/METADATA
calculator_775c57ddfd6f4cfb-0.0.2.dist-info/WHEEL
calculator_775c57ddfd6f4cfb-0.0.2.dist-info/top_level.txt
calculator_775c57ddfd6f4cfb-0.0.2.dist-info/RECORD
