Metadata-Version: 2.1
Name: calculator_775c57ddfd6f4cfb
Version: 0.0.2
Summary: A small example package for dependeny confusion
Author-email: Example Author <author@example.com>
Project-URL: Homepage, https://github.com/pypa/sampleproject
Project-URL: Bug Tracker, https://github.com/pypa/sampleproject/issues
Classifier: Programming Language :: Python :: 3
Classifier: License :: OSI Approved :: MIT License
Classifier: Operating System :: OS Independent
Requires-Python: >=3.7
